{
  "activities": {
    "19409929332": {
      "id": "19409929332",
      "athlete": "Erwin Hauw",
      "athleteId": "66730311",
      "startDate": "2026-07-21T21:21:16Z",
      "type": "Run",
      "distance_km": 10.5,
      "moving_time_sec": 3720,
      "distance_m": 10500
    },
    "19409957160": {
      "id": "19409957160",
      "athlete": "Toni Djiaw",
      "athleteId": "142218523",
      "startDate": "2026-07-21T21:39:09Z",
      "type": "Run",
      "distance_km": 6.07,
      "moving_time_sec": 2411,
      "distance_m": 6070
    },
    "19404077572": {
      "id": "19404077572",
      "athlete": "Christine .S",
      "athleteId": "71718168",
      "startDate": "2026-07-21T14:17:50Z",
      "type": "Run",
      "distance_km": 1.5,
      "moving_time_sec": 1230,
      "distance_m": 1500
    },
    "19404093259": {
      "id": "19404093259",
      "athlete": "Santi Kurniasari",
      "athleteId": "50128426",
      "startDate": "2026-07-21T13:07:38Z",
      "type": "Run",
      "distance_km": 10.19,
      "moving_time_sec": 5220,
      "distance_m": 10190
    },
    "19403830153": {
      "id": "19403830153",
      "athlete": "Aditra AL",
      "athleteId": "145979024",
      "startDate": "2026-07-21T12:55:47Z",
      "type": "Run",
      "distance_km": 12.02,
      "moving_time_sec": 4680,
      "distance_m": 12020
    },
    "19403450896": {
      "id": "19403450896",
      "athlete": "B A R A T LSP",
      "athleteId": "71432630",
      "startDate": "2026-07-21T11:36:49Z",
      "type": "Run",
      "distance_km": 14.13,
      "moving_time_sec": 7440,
      "distance_m": 14130
    },
    "19404608215": {
      "id": "19404608215",
      "athlete": "Cris Fe",
      "athleteId": "77575425",
      "startDate": "2026-07-20T17:00:01Z",
      "type": "Run",
      "distance_km": 12.43,
      "moving_time_sec": 6120,
      "distance_m": 12430
    },
    "19404048010": {
      "id": "19404048010",
      "athlete": "Yotta Risanggono",
      "athleteId": "125540711",
      "startDate": "2026-07-21T12:28:17Z",
      "type": "Run",
      "distance_km": 6.9,
      "moving_time_sec": 3900,
      "distance_m": 6900
    },
    "19403260676": {
      "id": "19403260676",
      "athlete": "Feri Yo",
      "athleteId": "119721281",
      "startDate": "2026-07-20T17:00:01Z",
      "type": "Run",
      "distance_km": 3.69,
      "moving_time_sec": 2679,
      "distance_m": 3690
    },
    "19403280524": {
      "id": "19403280524",
      "athlete": "Andree Setiawan",
      "athleteId": "95696517",
      "startDate": "2026-07-21T12:27:42Z",
      "type": "Run",
      "distance_km": 5.82,
      "moving_time_sec": 3416,
      "distance_m": 5820
    },
    "19403042168": {
      "id": "19403042168",
      "athlete": "Christine .S",
      "athleteId": "71718168",
      "startDate": "2026-07-21T12:00:08Z",
      "type": "Run",
      "distance_km": 12.02,
      "moving_time_sec": 4620,
      "distance_m": 12020
    },
    "19403044095": {
      "id": "19403044095",
      "athlete": "Gema Chrisdwianto",
      "athleteId": "135577017",
      "startDate": "2026-07-21T12:26:58Z",
      "type": "Run",
      "distance_km": 5,
      "moving_time_sec": 2786,
      "distance_m": 5000
    },
    "19403027446": {
      "id": "19403027446",
      "athlete": "Alex Rusman",
      "athleteId": "153243434",
      "startDate": "2026-07-21T11:59:55Z",
      "type": "Run",
      "distance_km": 12.02,
      "moving_time_sec": 4500,
      "distance_m": 12020
    },
    "19403006090": {
      "id": "19403006090",
      "athlete": "Arif Kurniawan",
      "athleteId": "19073451",
      "startDate": "2026-07-21T11:34:38Z",
      "type": "Run",
      "distance_km": 10.38,
      "moving_time_sec": 4860,
      "distance_m": 10380
    },
    "19403374449": {
      "id": "19403374449",
      "athlete": "Farhan Kastaa",
      "athleteId": "1390057573",
      "startDate": "2026-07-21T12:18:59Z",
      "type": "Run",
      "distance_km": 4.95,
      "moving_time_sec": 2224,
      "distance_m": 4950
    },
    "19402562899": {
      "id": "19402562899",
      "athlete": "Mohammad Nazir",
      "athleteId": "18323542",
      "startDate": "2026-07-21T11:31:39Z",
      "type": "Run",
      "distance_km": 10.04,
      "moving_time_sec": 3211,
      "distance_m": 10040
    },
    "19401948280": {
      "id": "19401948280",
      "athlete": "Farhan Kastaa",
      "athleteId": "1390057573",
      "startDate": "2026-07-21T10:42:40Z",
      "type": "Run",
      "distance_km": 10.37,
      "moving_time_sec": 3660,
      "distance_m": 10370
    },
    "19401479000": {
      "id": "19401479000",
      "athlete": "Erick Yanto",
      "athleteId": "164750862",
      "startDate": "2026-07-21T10:45:38Z",
      "type": "Run",
      "distance_km": 6.76,
      "moving_time_sec": 2655,
      "distance_m": 6760
    },
    "19401533861": {
      "id": "19401533861",
      "athlete": "Hendri Mulyadi",
      "athleteId": "137028433",
      "startDate": "2026-07-21T10:28:45Z",
      "type": "Run",
      "distance_km": 10.12,
      "moving_time_sec": 3600,
      "distance_m": 10120
    }
  }
}